{
  "name": "users/SZ3Yyiz1juketcDG7L6fdBdhnlLZ/docs/academic 2023-2024/Conversación con Pro.txt",
  "bucket": "eture-app-dev.appspot.com",
  "metageneration": 1,
  "generation": 1757429870023,
  "contentType": "text/plain",
  "storageClass": "STANDARD",
  "contentDisposition": "inline",
  "downloadTokens": [
    "43dfc6aa-985e-40d0-ba82-087705d8409b"
  ],
  "etag": "IzhGwOSMIs9CZe74hv0IWwH1vqs",
  "customMetadata": {},
  "timeCreated": "2025-09-09T14:57:50.023Z",
  "updated": "2025-09-09T14:57:50.023Z",
  "size": 1091850,
  "md5Hash": "bu9baGD7UxKG1l0Kw8zVyQ==",
  "crc32c": "3544407853"
}